ak_transcribe/__init__.py
ak_transcribe/console.py
ak_transcribe/converter.py
ak_transcribe/filehandler.py
ak_transcribe/transcriber.py
ak_transcribe/utils/config_parser.py
ak_transcribe-0.0.7.dist-info/LICENSE
ak_transcribe-0.0.7.dist-info/WHEEL
ak_transcribe-0.0.7.dist-info/METADATA
ak_transcribe-0.0.7.dist-info/RECORD
