Metadata-Version: 2.3
Name: ak_transcribe
Version: 0.0.7
Summary: Transcribe Media Files
Author-email: Arun Kishore <pypi@rpakishore.co.in>
Requires-Python: >=3.11.0
Classifier: License :: OSI Approved :: Mozilla Public License 2.0 (MPL 2.0)
Requires-Dist: groq>=0.18.0
Requires-Dist: requests
Requires-Dist: rich
Requires-Dist: openai-whisper ; extra == "cpu"
Requires-Dist: ipykernel ; extra == "dev"
Requires-Dist: ipywidgets ; extra == "dev"
Requires-Dist: pytest ; extra == "dev"
Project-URL: Home, https://github.com/rpakishore/ak_transcribe
Provides-Extra: cpu
Provides-Extra: dev
